{
"id": "FlowReg_deepfashion",
"gpu_ids": [
0
],
"which_model": "unet",
"init_type": "kaiming",
"norm": "batch",
"nf": 32,
"max_nf": 128,
"input_type1": "joint",
"input_type2": "joint",
"start_scale": 2,
"num_scale": 5,
"flow_loss_type": "l2",
"use_ss_flow_loss": 1,
"joint_nc": 18,
"joint_mode": "binary",
"joint_radius": 8,
"seg_nc": 7,
"dataset_type": "flow",
"dataset_name": "deepfashion",
"image_size": [
256,
256
],
"debug": false,
"aug_shiftx_range": 20,
"aug_shifty_range": 10,
"vis_smooth_rate": 5,
"resume_train": false,
"last_epoch": 1,
"pretrain_id": "",
"pretrain_epoch": "latest",
"lr": 0.0001,
"beta1": 0.9,
"beta2": 0.999,
"weight_decay": 0.0004,
"lr_policy": "step",
"n_epoch": 40,
"n_epoch_decay": 0,
"lr_decay": 8,
"lr_gamma": 0.5,
"display_freq": 10,
"test_epoch_freq": 1,
"save_epoch_freq": 5,
"vis_epoch_freq": 1,
"check_grad_freq": 100,
"n_vis": 64,
"loss_weight_flow": 1.0,
"loss_weight_vis": 1.0,
"loss_weight_flow_ss": 5.0,
"is_train": true
}